nrarfcn/__init__.py
nrarfcn/api/__init__.py
nrarfcn/api/get_bands_by_frequency.py
nrarfcn/api/get_bands_by_nrarfcn.py
nrarfcn/api/get_duplex_mode.py
nrarfcn/api/get_frequency.py
nrarfcn/api/get_frequency_by_gscn.py
nrarfcn/api/get_frequency_range.py
nrarfcn/api/get_gscn_by_frequency.py
nrarfcn/api/get_gscn_range.py
nrarfcn/api/get_nrarfcn.py
nrarfcn/api/get_nrarfcn_range.py
nrarfcn/tables/Table.py
nrarfcn/tables/__init__.py
nrarfcn/tables/applicable_nrarfcn_fr1.py
nrarfcn/tables/applicable_nrarfcn_fr2.py
nrarfcn/tables/applicable_ss_raster_fr1.py
nrarfcn/tables/applicable_ss_raster_fr2.py
nrarfcn/tables/bands_fr1.py
nrarfcn/tables/bands_fr2.py
nrarfcn/tables/freq_nrarfcn.py
nrarfcn/tables/gscn_parameters.py
nrarfcn-2.4.1.dist-info/licenses/LICENSE
nrarfcn-2.4.1.dist-info/METADATA
nrarfcn-2.4.1.dist-info/WHEEL
nrarfcn-2.4.1.dist-info/top_level.txt
nrarfcn-2.4.1.dist-info/RECORD
