Metadata-Version: 2.4
Name: nrarfcn
Version: 2.4.1
Summary: A 5G NR-ARFCN calculator
Author-email: Breno Levi <blevic@proton.me>
License: MIT License
Project-URL: Homepage, https://github.com/blevic/nrarfcn
Project-URL: Bug Tracker, https://github.com/blevic/nrarfcn/issues
Keywords: nrarfcn,arfcn,rf,radio,frequency,channel,5g,3gpp
Classifier: Programming Language :: Python :: 3
Classifier: License :: OSI Approved :: MIT License
Classifier: Operating System :: OS Independent
Requires-Python: >=3.6
License-File: LICENSE
Dynamic: license-file
